dicomrtai/__init__.py
dicomrtai/__main__.py
dicomrtai/_client.py
dicomrtai/_server.py
dicomrtai/proto/__init__.py
dicomrtai/proto/hello_world_pb2.py
dicomrtai/proto/hello_world_pb2.pyi
dicomrtai/proto/hello_world_pb2_grpc.py
dicomrtai-0.2.3.dist-info/entry_points.txt
dicomrtai-0.2.3.dist-info/LICENSE
dicomrtai-0.2.3.dist-info/WHEEL
dicomrtai-0.2.3.dist-info/METADATA
dicomrtai-0.2.3.dist-info/RECORD
